{
  "meta": {
    "totalMs": 1764700,
    "totalLoadMs": 0,
    "windowCount": 1212,
    "strategyCount": 39,
    "workers": 8
  },
  "table": [
    {
      "strategy": "mm-balanced-polyref",
      "symbol": "BTC",
      "trades": 2500,
      "winRate": 50.3,
      "totalPnl": 453.73,
      "sharpe": 2.86,
      "avgEntry": 0.473,
      "dollarPnl": 0.1815,
      "roc": 9.07,
      "pf": 1.18
    },
    {
      "strategy": "mm-balanced-wide",
      "symbol": "BTC",
      "trades": 3422,
      "winRate": 50.3,
      "totalPnl": 335.3,
      "sharpe": 2.25,
      "avgEntry": 0.4853,
      "dollarPnl": 0.098,
      "roc": 4.9,
      "pf": 1.1
    },
    {
      "strategy": "mm-bs-spread",
      "symbol": "BTC",
      "trades": 828,
      "winRate": 55.8,
      "totalPnl": 68.35,
      "sharpe": 0.74,
      "avgEntry": 0.5521,
      "dollarPnl": 0.0825,
      "roc": 4.13,
      "pf": 1.09
    },
    {
      "strategy": "mm-flipper-polyref",
      "symbol": "BTC",
      "trades": 7707,
      "winRate": 69,
      "totalPnl": -899.45,
      "sharpe": -2.68,
      "avgEntry": 0.4938,
      "dollarPnl": -0.1167,
      "roc": -5.84,
      "pf": 0.71
    },
    {
      "strategy": "mm-hedge-bs",
      "symbol": "BTC",
      "trades": 3095,
      "winRate": 54,
      "totalPnl": 131.41,
      "sharpe": 0.34,
      "avgEntry": 0.5419,
      "dollarPnl": 0.0425,
      "roc": 2.12,
      "pf": 1.05
    },
    {
      "strategy": "mm-hedge-clcross",
      "symbol": "BTC",
      "trades": 4757,
      "winRate": 52.4,
      "totalPnl": 75.04,
      "sharpe": 0.17,
      "avgEntry": 0.5231,
      "dollarPnl": 0.0158,
      "roc": 1.66,
      "pf": 1.04
    },
    {
      "strategy": "mm-hedge-coingecko",
      "symbol": "BTC",
      "trades": 3441,
      "winRate": 40.8,
      "totalPnl": -533.14,
      "sharpe": -0.86,
      "avgEntry": 0.4393,
      "dollarPnl": -0.1549,
      "roc": -7.75,
      "pf": 0.87
    },
    {
      "strategy": "mm-hedge-consensus",
      "symbol": "BTC",
      "trades": 0,
      "winRate": 0,
      "totalPnl": 0,
      "sharpe": 0,
      "avgEntry": 0,
      "dollarPnl": 0,
      "roc": 0,
      "pf": 0
    },
    {
      "strategy": "mm-hedge-exchange",
      "symbol": "BTC",
      "trades": 2744,
      "winRate": 48.8,
      "totalPnl": -6.9,
      "sharpe": -0.01,
      "avgEntry": 0.4968,
      "dollarPnl": -0.0025,
      "roc": -0.13,
      "pf": 1
    },
    {
      "strategy": "mm-hedge-polyref",
      "symbol": "BTC",
      "trades": 2889,
      "winRate": 49.5,
      "totalPnl": 381.98,
      "sharpe": 0.66,
      "avgEntry": 0.4885,
      "dollarPnl": 0.1322,
      "roc": 6.61,
      "pf": 1.13
    },
    {
      "strategy": "mm-hedge-vwap",
      "symbol": "BTC",
      "trades": 2725,
      "winRate": 51.2,
      "totalPnl": 62.69,
      "sharpe": 0.14,
      "avgEntry": 0.5177,
      "dollarPnl": 0.023,
      "roc": 1.15,
      "pf": 1.02
    },
    {
      "strategy": "mm-informed",
      "symbol": "BTC",
      "trades": 874,
      "winRate": 16.6,
      "totalPnl": 37.36,
      "sharpe": 0.57,
      "avgEntry": 0.5185,
      "dollarPnl": 0.0427,
      "roc": 2.14,
      "pf": 1.23
    },
    {
      "strategy": "mm-paired-10min",
      "symbol": "BTC",
      "trades": 7285,
      "winRate": 49.2,
      "totalPnl": 225.48,
      "sharpe": 0.66,
      "avgEntry": 0.4969,
      "dollarPnl": 0.031,
      "roc": 1.55,
      "pf": 1.03
    },
    {
      "strategy": "mm-paired-3min",
      "symbol": "BTC",
      "trades": 2609,
      "winRate": 43,
      "totalPnl": 365.18,
      "sharpe": 0.69,
      "avgEntry": 0.4385,
      "dollarPnl": 0.14,
      "roc": 7,
      "pf": 1.12
    },
    {
      "strategy": "mm-paired-asymmetric",
      "symbol": "BTC",
      "trades": 4054,
      "winRate": 46.7,
      "totalPnl": 293.69,
      "sharpe": 0.62,
      "avgEntry": 0.4697,
      "dollarPnl": 0.0724,
      "roc": 3.62,
      "pf": 1.07
    },
    {
      "strategy": "mm-paired-bs",
      "symbol": "BTC",
      "trades": 3934,
      "winRate": 49.2,
      "totalPnl": 23.53,
      "sharpe": 0.08,
      "avgEntry": 0.4986,
      "dollarPnl": 0.006,
      "roc": 0.3,
      "pf": 1.01
    },
    {
      "strategy": "mm-paired-confidence",
      "symbol": "BTC",
      "trades": 4039,
      "winRate": 46.8,
      "totalPnl": 292.08,
      "sharpe": 0.62,
      "avgEntry": 0.4706,
      "dollarPnl": 0.0723,
      "roc": 3.6,
      "pf": 1.07
    },
    {
      "strategy": "mm-paired-consensus",
      "symbol": "BTC",
      "trades": 252,
      "winRate": 46,
      "totalPnl": -25.26,
      "sharpe": -0.46,
      "avgEntry": 0.4766,
      "dollarPnl": -0.1002,
      "roc": -5.01,
      "pf": 0.91
    },
    {
      "strategy": "mm-paired-depthgate",
      "symbol": "BTC",
      "trades": 3788,
      "winRate": 45.3,
      "totalPnl": 146.25,
      "sharpe": 0.31,
      "avgEntry": 0.4607,
      "dollarPnl": 0.0386,
      "roc": 1.93,
      "pf": 1.04
    },
    {
      "strategy": "mm-paired-ensemble",
      "symbol": "BTC",
      "trades": 4004,
      "winRate": 46.7,
      "totalPnl": 58.35,
      "sharpe": 0.15,
      "avgEntry": 0.4739,
      "dollarPnl": 0.0146,
      "roc": 0.73,
      "pf": 1.01
    },
    {
      "strategy": "mm-paired-exchange",
      "symbol": "BTC",
      "trades": 3765,
      "winRate": 46.4,
      "totalPnl": -80.48,
      "sharpe": -0.22,
      "avgEntry": 0.4746,
      "dollarPnl": -0.0214,
      "roc": -1.07,
      "pf": 0.98
    },
    {
      "strategy": "mm-paired-exit-both",
      "symbol": "BTC",
      "trades": 4044,
      "winRate": 46.9,
      "totalPnl": 0,
      "sharpe": 0,
      "avgEntry": 0.4705,
      "dollarPnl": 0,
      "roc": 0,
      "pf": 1.06
    },
    {
      "strategy": "mm-paired-exit-losers",
      "symbol": "BTC",
      "trades": 4044,
      "winRate": 35,
      "totalPnl": 738.65,
      "sharpe": 1.9,
      "avgEntry": 0.4705,
      "dollarPnl": 0.1827,
      "roc": 9.13,
      "pf": 1.35
    },
    {
      "strategy": "mm-paired-exit-unmatched",
      "symbol": "BTC",
      "trades": 4044,
      "winRate": 47.5,
      "totalPnl": 0,
      "sharpe": 0,
      "avgEntry": 0.4705,
      "dollarPnl": 0,
      "roc": 0,
      "pf": 1.1
    },
    {
      "strategy": "mm-paired-fastcooldown",
      "symbol": "BTC",
      "trades": 4437,
      "winRate": 48.4,
      "totalPnl": 308.31,
      "sharpe": 0.66,
      "avgEntry": 0.4816,
      "dollarPnl": 0.0695,
      "roc": 3.47,
      "pf": 1.07
    },
    {
      "strategy": "mm-paired-invconfidence",
      "symbol": "BTC",
      "trades": 4647,
      "winRate": 46.5,
      "totalPnl": 326.04,
      "sharpe": 0.59,
      "avgEntry": 0.4674,
      "dollarPnl": 0.0702,
      "roc": 3.52,
      "pf": 1.07
    },
    {
      "strategy": "mm-paired-kelly",
      "symbol": "BTC",
      "trades": 5846,
      "winRate": 46.1,
      "totalPnl": 57.11,
      "sharpe": 0.18,
      "avgEntry": 0.4543,
      "dollarPnl": 0.0098,
      "roc": 0.78,
      "pf": 1.01
    },
    {
      "strategy": "mm-paired-latehedge",
      "symbol": "BTC",
      "trades": 3816,
      "winRate": 47.1,
      "totalPnl": -23.39,
      "sharpe": -0.07,
      "avgEntry": 0.4781,
      "dollarPnl": -0.0061,
      "roc": -0.31,
      "pf": 0.99
    },
    {
      "strategy": "mm-paired-maxunmatched",
      "symbol": "BTC",
      "trades": 3748,
      "winRate": 48.3,
      "totalPnl": 185.12,
      "sharpe": 0.64,
      "avgEntry": 0.4847,
      "dollarPnl": 0.0494,
      "roc": 2.47,
      "pf": 1.05
    },
    {
      "strategy": "mm-paired-momentum",
      "symbol": "BTC",
      "trades": 4182,
      "winRate": 47.1,
      "totalPnl": 223.16,
      "sharpe": 0.52,
      "avgEntry": 0.4732,
      "dollarPnl": 0.0534,
      "roc": 2.67,
      "pf": 1.05
    },
    {
      "strategy": "mm-paired-nocooldown",
      "symbol": "BTC",
      "trades": 9661,
      "winRate": 49.1,
      "totalPnl": 596.91,
      "sharpe": 0.91,
      "avgEntry": 0.4877,
      "dollarPnl": 0.0618,
      "roc": 6.18,
      "pf": 1.12
    },
    {
      "strategy": "mm-paired-polyref",
      "symbol": "BTC",
      "trades": 4044,
      "winRate": 46.8,
      "totalPnl": 289.81,
      "sharpe": 0.62,
      "avgEntry": 0.4705,
      "dollarPnl": 0.0717,
      "roc": 3.58,
      "pf": 1.07
    },
    {
      "strategy": "mm-paired-strict",
      "symbol": "BTC",
      "trades": 3491,
      "winRate": 48.9,
      "totalPnl": 81.87,
      "sharpe": 0.44,
      "avgEntry": 0.4939,
      "dollarPnl": 0.0235,
      "roc": 1.17,
      "pf": 1.02
    },
    {
      "strategy": "mm-paired-timedecay",
      "symbol": "BTC",
      "trades": 3994,
      "winRate": 46.6,
      "totalPnl": 293.18,
      "sharpe": 0.62,
      "avgEntry": 0.468,
      "dollarPnl": 0.0734,
      "roc": 3.67,
      "pf": 1.07
    },
    {
      "strategy": "mm-paired-volregime",
      "symbol": "BTC",
      "trades": 4009,
      "winRate": 46.9,
      "totalPnl": 248.86,
      "sharpe": 0.54,
      "avgEntry": 0.4714,
      "dollarPnl": 0.0621,
      "roc": 3.1,
      "pf": 1.06
    },
    {
      "strategy": "mm-paired-vwap",
      "symbol": "BTC",
      "trades": 4004,
      "winRate": 46.7,
      "totalPnl": 58.35,
      "sharpe": 0.15,
      "avgEntry": 0.4739,
      "dollarPnl": 0.0146,
      "roc": 0.73,
      "pf": 1.01
    },
    {
      "strategy": "mm-rebalance-polyref",
      "symbol": "BTC",
      "trades": 3407,
      "winRate": 48.6,
      "totalPnl": 133.84,
      "sharpe": 0.62,
      "avgEntry": 0.4888,
      "dollarPnl": 0.0393,
      "roc": 1.86,
      "pf": 1.04
    },
    {
      "strategy": "mm-spreadcapture",
      "symbol": "BTC",
      "trades": 2500,
      "winRate": 50.3,
      "totalPnl": 453.73,
      "sharpe": 2.86,
      "avgEntry": 0.473,
      "dollarPnl": 0.1815,
      "roc": 9.07,
      "pf": 1.18
    },
    {
      "strategy": "mm-twoway-polyref",
      "symbol": "BTC",
      "trades": 9462,
      "winRate": 63.5,
      "totalPnl": -1819.89,
      "sharpe": -4.66,
      "avgEntry": 0.4798,
      "dollarPnl": -0.1923,
      "roc": -9.62,
      "pf": 0.6
    }
  ]
}